npqtools/UI.py
npqtools/__init__.py
npqtools/test.py
npqtools/problems/PrintGraph.py
npqtools/problems/QuboClique.py
npqtools/problems/QuboKnapsack.py
npqtools/problems/QuboMaxWeightClique.py
npqtools/problems/QuboMultiKnapsack.py
npqtools/problems/QuboProductionScheduling.py
npqtools/problems/QuboSalesman.py
npqtools/problems/QuboTiling2Dim.py
npqtools/problems/__init__.py
npqtools/problems/qubo.py
npqtools-0.1.15.dist-info/METADATA
npqtools-0.1.15.dist-info/WHEEL
npqtools-0.1.15.dist-info/top_level.txt
npqtools-0.1.15.dist-info/RECORD
