Metadata-Version: 2.1
Name: npqtools
Version: 0.1.15
Summary: Library for reinterpretation main np-problems into Ising model for quantum computer
Home-page: https://gitverse.ru/mits2406/npqtools
Author: Mikhail Tseytlin
Author-email: tseytlinmikhail@gmail.com
Classifier: Programming Language :: Python :: 3
Classifier: License :: OSI Approved :: MIT License
Classifier: Operating System :: OS Independent
Requires-Python: >=3.6
Requires-Dist: numpy >=2.0.2
Requires-Dist: matplotlib >=3.9.2
Requires-Dist: dimod >=0.12.18
Requires-Dist: dwave-samplers >=1.4.0
